literobo-0.1.7.dist-info/METADATA
literobo-0.1.7.dist-info/WHEEL
literobo/__init__.py
literobo/literobo.abi3.so
literobo-0.1.7.dist-info/RECORD
