Metadata-Version: 2.4
Name: literobo
Version: 0.1.7
Classifier: Programming Language :: Rust
Classifier: Programming Language :: Python :: 3
Classifier: License :: OSI Approved :: MIT License
Classifier: Operating System :: OS Independent
Requires-Dist: maturin ; extra == 'dev'
Requires-Dist: numpy>=1.20 ; extra == 'dev'
Requires-Dist: pytest ; extra == 'dev'
Requires-Dist: numpy>=1.20 ; extra == 'test'
Requires-Dist: pytest ; extra == 'test'
Provides-Extra: dev
Provides-Extra: test
Summary: Lightweight URDF kinematics (forward kinematics + Jacobian) with Rust speed and Python bindings.
Author: literobo contributors
License: MIT
Requires-Python: >=3.8
